pfeiffer_vacuum_protocol/__init__.py
pfeiffer_vacuum_protocol/mock.py
pfeiffer_vacuum_protocol/pfeiffer_vacuum_protocol.py
pfeiffer_vacuum_protocol-1.0.dist-info/LICENSE.txt
pfeiffer_vacuum_protocol-1.0.dist-info/METADATA
pfeiffer_vacuum_protocol-1.0.dist-info/WHEEL
pfeiffer_vacuum_protocol-1.0.dist-info/top_level.txt
pfeiffer_vacuum_protocol-1.0.dist-info/RECORD
