Metadata-Version: 2.1
Name: pfeiffer-vacuum-protocol
Version: 1.0
Summary: Python interface to Pfeiffer vacuum gauges
Author-email: "Christopher M. Pierce" <contact@chris-pierce.com>
License: BSD 3-Clause License
Classifier: Programming Language :: Python :: 3
Classifier: Operating System :: OS Independent
Classifier: License :: OSI Approved :: BSD License
Requires-Python: >=3.6
License-File: LICENSE.txt
